muslimdeenV2/__init__.py
muslimdeenV2/ablutions.py
muslimdeenV2/config.py
muslimdeenV2/data_salat.py
muslimdeenV2/exception_handle.py
muslimdeenV2/meta_quran_reader.py
muslimdeenV2/metasurahs.py
muslimdeenV2/names_of_allah.py
muslimdeenV2/pillards_of_islam.py
muslimdeenV2/pillars_of_islam.py
muslimdeenV2/quran_reader.py
muslimdeenV2/salat.py
muslimdeenV2/services.py
muslimdeenV2/zakat.py
muslimdeenV2-2.0.6.dist-info/METADATA
muslimdeenV2-2.0.6.dist-info/WHEEL
muslimdeenV2-2.0.6.dist-info/top_level.txt
muslimdeenV2-2.0.6.dist-info/RECORD
