Metadata-Version: 2.1
Name: muslimdeenV2
Version: 2.0.6
Summary: MuslimDeen: Package pour gérer les sourates, noms d'Allah, ablutions et salat
Home-page: https://gitlab.com/misternobody01/muslimdeen#
Author: personne monsieur
Author-email: monsieurnobody01@gmail.com
Classifier: Programming Language :: Python :: 3
Classifier: License :: OSI Approved :: MIT License
Classifier: Operating System :: OS Independent
Requires-Python: >=3.6
Requires-Dist: attrs==23.2.0
Requires-Dist: Babel==2.10.3
Requires-Dist: bcc==0.29.1
Requires-Dist: bcrypt==3.2.2
Requires-Dist: blinker==1.7.0
Requires-Dist: Brlapi==0.8.5
Requires-Dist: certifi==2023.11.17
Requires-Dist: chardet==5.2.0
Requires-Dist: click==8.1.6
Requires-Dist: cloud-init==24.3.1
Requires-Dist: colorama==0.4.6
Requires-Dist: command-not-found==0.3
Requires-Dist: configobj==5.0.8
Requires-Dist: cryptography==41.0.7
Requires-Dist: cupshelpers==1.0
Requires-Dist: dbus-python==1.3.2
Requires-Dist: defer==1.0.6
Requires-Dist: distro==1.9.0
Requires-Dist: distro-info==1.7+build1
Requires-Dist: duplicity==2.1.4
Requires-Dist: fasteners==0.18
Requires-Dist: httplib2==0.20.4
Requires-Dist: idna==3.6
Requires-Dist: Jinja2==3.1.2
Requires-Dist: jsonpatch==1.32
Requires-Dist: jsonpointer==2.0
Requires-Dist: jsonschema==4.10.3
Requires-Dist: language-selector==0.1
Requires-Dist: launchpadlib==1.11.0
Requires-Dist: lazr.restfulclient==0.14.6
Requires-Dist: lazr.uri==1.0.6
Requires-Dist: louis==3.29.0
Requires-Dist: Mako==1.3.2.dev0
Requires-Dist: markdown-it-py==3.0.0
Requires-Dist: MarkupSafe==2.1.5
Requires-Dist: mdurl==0.1.2
Requires-Dist: mercurial==6.7.2
Requires-Dist: monotonic==1.6
Requires-Dist: netaddr==0.8.0
Requires-Dist: netifaces==0.11.0
Requires-Dist: oauthlib==3.2.2
Requires-Dist: olefile==0.46
Requires-Dist: packaging==24.0
Requires-Dist: paramiko==2.12.0
Requires-Dist: pexpect==4.9.0
Requires-Dist: pillow==10.2.0
Requires-Dist: ptyprocess==0.7.0
Requires-Dist: pycairo==1.25.1
Requires-Dist: pycups==2.0.1
Requires-Dist: Pygments==2.17.2
Requires-Dist: PyGObject==3.48.2
Requires-Dist: PyJWT==2.7.0
Requires-Dist: PyNaCl==1.5.0
Requires-Dist: pyparsing==3.1.1
Requires-Dist: pyrsistent==0.20.0
Requires-Dist: pyserial==3.5
Requires-Dist: python-apt==2.7.7+ubuntu3
Requires-Dist: python-dateutil==2.8.2
Requires-Dist: python-debian==0.1.49+ubuntu2
Requires-Dist: pytz==2024.1
Requires-Dist: pyxdg==0.28
Requires-Dist: PyYAML==6.0.1
Requires-Dist: requests==2.31.0
Requires-Dist: rich==13.7.1
Requires-Dist: setuptools==68.1.2
Requires-Dist: six==1.16.0
Requires-Dist: systemd-python==235
Requires-Dist: typing_extensions==4.10.0
Requires-Dist: ubuntu-drivers-common==0.0.0
Requires-Dist: ubuntu-pro-client==8001
Requires-Dist: ufw==0.36.2
Requires-Dist: unattended-upgrades==0.1
Requires-Dist: urllib3==2.0.7
Requires-Dist: usb-creator==0.3.16
Requires-Dist: wadllib==1.3.6
Requires-Dist: wheel==0.42.0
Requires-Dist: xdg==5
Requires-Dist: xkit==0.0.0
